awslabs/__init__.py
awslabs/timestream_for_influxdb_mcp_server/__init__.py
awslabs/timestream_for_influxdb_mcp_server/server.py
awslabs_timestream_for_influxdb_mcp_server-0.0.12.dist-info/METADATA
awslabs_timestream_for_influxdb_mcp_server-0.0.12.dist-info/WHEEL
awslabs_timestream_for_influxdb_mcp_server-0.0.12.dist-info/entry_points.txt
awslabs_timestream_for_influxdb_mcp_server-0.0.12.dist-info/licenses/LICENSE
awslabs_timestream_for_influxdb_mcp_server-0.0.12.dist-info/licenses/NOTICE
awslabs_timestream_for_influxdb_mcp_server-0.0.12.dist-info/RECORD
